{
  "hash": "e0327b8c",
  "browserHash": "9ee50162",
  "optimized": {
    "react": {
      "src": "../../node_modules/react/index.js",
      "file": "react.js",
      "fileHash": "98fc573e",
      "needsInterop": true
    },
    "react-dom/client": {
      "src": "../../node_modules/react-dom/client.js",
      "file": "react-dom_client.js",
      "fileHash": "fa1f153c",
      "needsInterop": true
    },
    "react-redux": {
      "src": "../../node_modules/react-redux/es/index.js",
      "file": "react-redux.js",
      "fileHash": "90a4393e",
      "needsInterop": false
    },
    "@reduxjs/toolkit": {
      "src": "../../node_modules/@reduxjs/toolkit/dist/redux-toolkit.esm.js",
      "file": "@reduxjs_toolkit.js",
      "fileHash": "a6c83cf7",
      "needsInterop": false
    }
  },
  "chunks": {
    "chunk-DZXRV6RW": {
      "file": "chunk-DZXRV6RW.js"
    },
    "chunk-ZAUFE7H7": {
      "file": "chunk-ZAUFE7H7.js"
    },
    "chunk-UXIASGQL": {
      "file": "chunk-UXIASGQL.js"
    }
  }
}